monstereo/__init__.py
monstereo/activity.py
monstereo/predict.py
monstereo/run.py
monstereo/eval/__init__.py
monstereo/eval/eval_activity.py
monstereo/eval/eval_kitti.py
monstereo/eval/eval_variance.py
monstereo/eval/generate_kitti.py
monstereo/eval/reid_baseline.py
monstereo/eval/stereo_baselines.py
monstereo/network/__init__.py
monstereo/network/architectures.py
monstereo/network/geom_baseline.py
monstereo/network/net.py
monstereo/network/pifpaf.py
monstereo/network/process.py
monstereo/prep/__init__.py
monstereo/prep/prep_kitti.py
monstereo/prep/preprocess_nu.py
monstereo/prep/transforms.py
monstereo/train/__init__.py
monstereo/train/datasets.py
monstereo/train/hyp_tuning.py
monstereo/train/losses.py
monstereo/train/trainer.py
monstereo/utils/__init__.py
monstereo/utils/camera.py
monstereo/utils/iou.py
monstereo/utils/kitti.py
monstereo/utils/logs.py
monstereo/utils/misc.py
monstereo/utils/nuscenes.py
monstereo/utils/stereo.py
monstereo/visuals/__init__.py
monstereo/visuals/figures.py
monstereo/visuals/pifpaf_show.py
monstereo/visuals/plot_3d_box.py
monstereo/visuals/printer.py
monstereo-0.2.3.dist-info/LICENSE
monstereo-0.2.3.dist-info/LICENSE.AGPL
monstereo-0.2.3.dist-info/METADATA
monstereo-0.2.3.dist-info/WHEEL
monstereo-0.2.3.dist-info/top_level.txt
monstereo-0.2.3.dist-info/RECORD
