Metadata-Version: 2.1
Name: monstereo
Version: 0.2.3
Summary: Perceiving Humans: from Monocular 3D Localization to Social Distancing / MonStereo: When Monocular and Stereo Meet at the Tail of 3D Human Localization
Home-page: https://github.com/vita-epfl/monstereo
Author: Lorenzo Bertoni
Author-email: lorenzo.bertoni@epfl.ch
License: GNU AGPLv3
Platform: UNKNOWN
Requires-Dist: openpifpaf (==v0.12.1)
Requires-Dist: matplotlib
Provides-Extra: eval
Requires-Dist: tabulate (==0.8.3) ; extra == 'eval'
Requires-Dist: sklearn ; extra == 'eval'
Requires-Dist: pandas ; extra == 'eval'
Requires-Dist: pylint ; extra == 'eval'
Requires-Dist: pytest ; extra == 'eval'
Provides-Extra: prep
Requires-Dist: nuscenes-devkit (==1.0.2) ; extra == 'prep'
